testbench/__init__.py
testbench/ssh.py
testbench/virtualbox.py
testbench-0.1.2.dist-info/LICENSE
testbench-0.1.2.dist-info/METADATA
testbench-0.1.2.dist-info/WHEEL
testbench-0.1.2.dist-info/top_level.txt
testbench-0.1.2.dist-info/RECORD
